jsonc2json-0.0.4.dist-info/METADATA
jsonc2json-0.0.4.dist-info/WHEEL
jsonc2json/__init__.py
jsonc2json/py.typed
jsonc2json/__main__.py
jsonc2json/_jsonc2json.pyi
jsonc2json/_jsonc2json.cpython-39-aarch64-linux-gnu.so
jsonc2json-0.0.4.dist-info/RECORD
