Metadata-Version: 2.3
Name: jsonc2json
Version: 0.0.4
Classifier: Programming Language :: Rust
Classifier: Programming Language :: Python :: Implementation :: CPython
Classifier: Programming Language :: Python :: Implementation :: PyPy
Classifier: Programming Language :: Python :: 3
Summary: jsonc2json ~ convert jsonc 2 json ~ python + rust
Keywords: json,jsonc,rust,pyo3
Author-email: Jesse Rubin <jessekrubin@gmail.com>
Maintainer-email: Jesse Rubin <jessekrubin@gmail.com>
License: MIT OR Apache-2.0
Requires-Python: >=3.8
Project-URL: documentation, https://github.com/jessekrubin/jsonc2json
Project-URL: homepage, https://github.com/jessekrubin/jsonc2json
Project-URL: source, https://github.com/jessekrubin/jsonc2json
